gradio_test2/__init__.py
gradio_test2/test2.py
gradio_test2/test2.pyi
gradio_test2/templates/component/index.js
gradio_test2/templates/component/style.css
gradio_test2/templates/example/index.js
gradio_test2/templates/example/style.css
gradio_test2-0.0.2.dist-info/METADATA
gradio_test2-0.0.2.dist-info/WHEEL
gradio_test2-0.0.2.dist-info/RECORD
